{"data_mtime":1759640768,"dep_lines":[43,44,57,59,186,36,37,39,39,39,40,41,42,45,46,47,54,56,58,72,1,2,3,4,5,6,7,8,9,10,12,13,14,33,39,1,1,1,1,1,1,1,1,1,1,1,1,1,1,1,1,1,1,1,1,1,1,1,1,1,1,1,1,1,1,1,1,1,1,1,1,1,1,1,1,1,1,1,1,1,1,1,1,1,35,55,71,34],"dep_prios":[5,5,5,5,20,5,5,10,10,5,5,5,5,5,5,5,5,5,5,5,10,10,5,10,10,10,10,5,5,5,5,5,5,10,20,5,20,20,20,20,20,20,20,20,20,20,20,20,20,20,20,20,20,20,20,20,20,30,30,30,30,30,30,30,30,30,30,30,30,30,30,30,30,30,30,30,30,30,30,30,30,30,30,30,5,5,5,10],"dependencies":["spacy.lang.punctuation","spacy.lang.tokenizer_exceptions","spacy.tokens.underscore","spacy.training.initialize","spacy.pipeline.factories","thinc.api","thinc.util","spacy.about","spacy.ty","spacy.util","spacy.compat","spacy.errors","spacy.git_info","spacy.lookups","spacy.pipe_analysis","spacy.schemas","spacy.scorer","spacy.tokens","spacy.training","spacy.vocab","functools","inspect","itertools","multiprocessing","random","traceback","warnings","contextlib","copy","dataclasses","pathlib","timeit","typing","numpy","spacy","builtins","pydot","logging","re","os","html","string","torch.nn","pprint","multiprocessing.reduction","subprocess","torch.distributed._functional_collectives","torch","types","math","collections","pydot._vendor.tempfile","errno","sys","operator","transformers.utils.logging","torch.distributed","_collections_abc","_frozen_importlib","_typeshed","_warnings","abc","confection","configparser","multiprocessing.connection","multiprocessing.context","multiprocessing.process","multiprocessing.queues","pydantic","pydantic.v1","pydantic.v1.main","pydantic.v1.utils","spacy.pipeline","spacy.strings","spacy.tokens.doc","spacy.tokens.span","spacy.tokens.token","spacy.training.example","thinc","thinc.backends","thinc.backends.ops","thinc.config","thinc.model","thinc.optimizers"],"hash":"90338572276e68cf416cfa468c1ec394a4535c81","id":"spacy.language","ignore_all":true,"interface_hash":"579bddfb7327d6b24f85bd0803fb905a04706223","mtime":1759613578,"options":{"allow_redefinition":false,"allow_untyped_globals":false,"always_false":[],"always_true":[],"bazel":false,"check_untyped_defs":false,"disable_bytearray_promotion":false,"disable_error_code":[],"disable_memoryview_promotion":false,"disabled_error_codes":[],"disallow_any_decorated":false,"disallow_any_explicit":false,"disallow_any_expr":false,"disallow_any_generics":false,"disallow_any_unimported":false,"disallow_incomplete_defs":false,"disallow_subclassing_any":false,"disallow_untyped_calls":false,"disallow_untyped_decorators":false,"disallow_untyped_defs":false,"enable_error_code":[],"enabled_error_codes":[],"extra_checks":false,"follow_imports":"normal","follow_imports_for_stubs":false,"follow_untyped_imports":false,"ignore_errors":false,"ignore_missing_imports":false,"implicit_optional":false,"implicit_reexport":true,"local_partial_types":false,"mypyc":false,"old_type_inference":false,"platform":"darwin","plugins":[],"strict_bytes":false,"strict_concatenate":false,"strict_equality":false,"strict_optional":true,"warn_no_return":true,"warn_return_any":false,"warn_unreachable":false,"warn_unused_ignores":false},"path":"/Users/yassraasim/.pyenv/versions/3.12.11/lib/python3.12/site-packages/spacy/language.py","plugin_data":null,"size":106750,"suppressed":["cymem.cymem","spacy.tokenizer","spacy.vectors","srsly"],"version_id":"1.15.0"}